{
  "_comment" : "Created with OWL2VOWL (version 0.3.7), http://vowl.visualdataweb.org",
  "header" : {
    "languages" : [ "en", "undefined" ],
    "baseIris" : [ "https://w3id.org/mdo/provenance", "http://www.w3.org/1999/02/22-rdf-syntax-ns", "https://w3id.org/mdo/core", "http://emmo.info/domains/emmo-material.owl", "http://www.w3.org/2000/01/rdf-schema", "http://www.w3.org/ns/prov", "http://www.w3.org/2001/XMLSchema" ],
    "prefixList" : {
      "owl" : "http://www.w3.org/2002/07/owl#",
      "emmo" : "http://emmo.info/domains/emmo-material.owl#",
      "rdf" : "http://www.w3.org/1999/02/22-rdf-syntax-ns#",
      "vann" : "http://purl.org/vocab/vann/",
      "dcterms" : "http://purl.org/dc/terms/",
      "xsd" : "http://www.w3.org/2001/XMLSchema#",
      "" : "https://w3id.org/mdo/core/",
      "xml" : "http://www.w3.org/XML/1998/namespace",
      "rdfs" : "http://www.w3.org/2000/01/rdf-schema#"
    },
    "title" : {
      "en" : "Materials Design Ontology - Provenance Module"
    },
    "iri" : "https://w3id.org/mdo/provenance/",
    "version" : "1.0",
    "author" : [ "Huanyu Li" ],
    "comments" : {
      "en" : "This is the provenance module of Materials Design Ontology."
    },
    "other" : {
      "license" : [ {
        "identifier" : "license",
        "language" : "undefined",
        "value" : "https://github.com/huanyu-li/Materials-Design-Ontology/blob/master/LICENSE",
        "type" : "label"
      } ],
      "creator" : [ {
        "identifier" : "creator",
        "language" : "undefined",
        "value" : "Huanyu Li",
        "type" : "label"
      } ],
      "contributor" : [ {
        "identifier" : "contributor",
        "language" : "undefined",
        "value" : "Patrick Lambrix",
        "type" : "label"
      }, {
        "identifier" : "contributor",
        "language" : "undefined",
        "value" : "Rickard Armiento",
        "type" : "label"
      } ],
      "created" : [ {
        "identifier" : "created",
        "language" : "undefined",
        "value" : "2020-04-02",
        "type" : "label"
      } ],
      "preferredNamespacePrefix" : [ {
        "identifier" : "preferredNamespacePrefix",
        "language" : "undefined",
        "value" : "provenance",
        "type" : "label"
      } ],
      "versionInfo" : [ {
        "identifier" : "versionInfo",
        "language" : "undefined",
        "value" : "1.0",
        "type" : "label"
      } ],
      "preferredNamespaceUri" : [ {
        "identifier" : "preferredNamespaceUri",
        "language" : "undefined",
        "value" : "https://w3id.org/mdo/provenance/1.0",
        "type" : "label"
      } ],
      "title" : [ {
        "identifier" : "title",
        "language" : "en",
        "value" : "Materials Design Ontology - Provenance Module",
        "type" : "label"
      } ],
      "seeAlso" : [ {
        "identifier" : "seeAlso",
        "language" : "undefined",
        "value" : "https://github.com/huanyu-li/Materials-Design-Ontology",
        "type" : "label"
      } ]
    }
  },
  "namespace" : [ ],
  "class" : [ {
    "id" : "7",
    "type" : "owl:Class"
  }, {
    "id" : "10",
    "type" : "owl:Class"
  }, {
    "id" : "14",
    "type" : "owl:Thing"
  }, {
    "id" : "15",
    "type" : "rdfs:Datatype"
  }, {
    "id" : "18",
    "type" : "owl:Class"
  }, {
    "id" : "2",
    "type" : "rdfs:Datatype"
  }, {
    "id" : "17",
    "type" : "owl:Class"
  }, {
    "id" : "20",
    "type" : "rdfs:Datatype"
  }, {
    "id" : "21",
    "type" : "rdfs:Datatype"
  }, {
    "id" : "5",
    "type" : "owl:Class"
  }, {
    "id" : "22",
    "type" : "owl:Class"
  }, {
    "id" : "4",
    "type" : "owl:Class"
  }, {
    "id" : "27",
    "type" : "owl:unionOf"
  }, {
    "id" : "29",
    "type" : "rdfs:Datatype"
  }, {
    "id" : "32",
    "type" : "rdfs:Datatype"
  }, {
    "id" : "9",
    "type" : "rdfs:Datatype"
  }, {
    "id" : "31",
    "type" : "rdfs:Datatype"
  }, {
    "id" : "33",
    "type" : "rdfs:Datatype"
  }, {
    "id" : "25",
    "type" : "rdfs:Datatype"
  }, {
    "id" : "35",
    "type" : "rdfs:Datatype"
  }, {
    "id" : "1",
    "type" : "owl:Class"
  }, {
    "id" : "12",
    "type" : "owl:Class"
  } ],
  "classAttribute" : [ {
    "iri" : "https://w3id.org/mdo/core/Calculation",
    "baseIri" : "https://w3id.org/mdo/core",
    "instances" : 0,
    "label" : {
      "IRI-based" : "Calculation"
    },
    "comment" : {
      "en" : "A calculation is the use of a specific computational method to process structures and/or properties into output structures and/or calculated properties."
    },
    "attributes" : [ "external" ],
    "id" : "7"
  }, {
    "iri" : "https://w3id.org/mdo/core/CalculatedProperty",
    "baseIri" : "https://w3id.org/mdo/core",
    "instances" : 0,
    "label" : {
      "IRI-based" : "CalculatedProperty"
    },
    "comment" : {
      "en" : "Properties of structures or materials that are influenced by calculations."
    },
    "attributes" : [ "external" ],
    "id" : "10",
    "superClasses" : [ "4" ]
  }, {
    "iri" : "http://www.w3.org/2002/07/owl#Thing",
    "baseIri" : "http://owl2vowl.de",
    "id" : "14",
    "label" : {
      "undefined" : "Thing"
    }
  }, {
    "iri" : "http://www.w3.org/2001/XMLSchema#string",
    "baseIri" : "http://www.w3.org/2001/XMLSchema",
    "id" : "15",
    "label" : {
      "IRI-based" : "string"
    }
  }, {
    "iri" : "http://www.w3.org/ns/prov#Agent",
    "baseIri" : "http://www.w3.org/ns/prov",
    "instances" : 0,
    "label" : {
      "IRI-based" : "Agent"
    },
    "subClasses" : [ "1", "17" ],
    "attributes" : [ "external" ],
    "id" : "18"
  }, {
    "iri" : "http://www.w3.org/2001/XMLSchema#string",
    "baseIri" : "http://www.w3.org/2001/XMLSchema",
    "id" : "2",
    "label" : {
      "IRI-based" : "string"
    }
  }, {
    "iri" : "http://www.w3.org/ns/prov#SoftwareAgent",
    "baseIri" : "http://www.w3.org/ns/prov",
    "instances" : 0,
    "label" : {
      "IRI-based" : "SoftwareAgent"
    },
    "comment" : {
      "en" : "A software agent is the representation of the software that produces the result of a material calculation."
    },
    "attributes" : [ "external" ],
    "id" : "17",
    "superClasses" : [ "18" ]
  }, {
    "iri" : "http://www.w3.org/2001/XMLSchema#string",
    "baseIri" : "http://www.w3.org/2001/XMLSchema",
    "id" : "20",
    "label" : {
      "IRI-based" : "string"
    }
  }, {
    "iri" : "http://www.w3.org/2001/XMLSchema#string",
    "baseIri" : "http://www.w3.org/2001/XMLSchema",
    "id" : "21",
    "label" : {
      "IRI-based" : "string"
    }
  }, {
    "iri" : "https://w3id.org/mdo/core/Structure",
    "baseIri" : "https://w3id.org/mdo/core",
    "instances" : 0,
    "label" : {
      "IRI-based" : "Structure"
    },
    "comment" : {
      "en" : "A structure is the information of the sites and their occupancies in a material or materials system."
    },
    "attributes" : [ "external" ],
    "id" : "5"
  }, {
    "iri" : "http://emmo.info/domains/emmo-material.owl#EMMO_4207e895_8b83_4318_996a_72cfb32acd94",
    "baseIri" : "http://emmo.info/domains/emmo-material.owl",
    "instances" : 0,
    "label" : {
      "IRI-based" : "EMMO_4207e895_8b83_4318_996a_72cfb32acd94",
      "undefined" : "Material"
    },
    "attributes" : [ "external" ],
    "id" : "22"
  }, {
    "iri" : "https://w3id.org/mdo/core/Property",
    "baseIri" : "https://w3id.org/mdo/core",
    "instances" : 0,
    "annotations" : {
      "seeAlso" : [ {
        "identifier" : "seeAlso",
        "language" : "en",
        "value" : "https://en.wikipedia.org/wiki/List_of_materials_properties",
        "type" : "label"
      } ]
    },
    "label" : {
      "IRI-based" : "Property"
    },
    "subClasses" : [ "10", "12" ],
    "comment" : {
      "en" : "A property in materials design is data pertaining to at least one material or materials system."
    },
    "attributes" : [ "external" ],
    "id" : "4"
  }, {
    "instances" : 0,
    "union" : [ "7", "5" ],
    "attributes" : [ "anonymous", "union" ],
    "id" : "27"
  }, {
    "iri" : "http://www.w3.org/2001/XMLSchema#string",
    "baseIri" : "http://www.w3.org/2001/XMLSchema",
    "id" : "29",
    "label" : {
      "IRI-based" : "string"
    }
  }, {
    "iri" : "http://www.w3.org/2001/XMLSchema#string",
    "baseIri" : "http://www.w3.org/2001/XMLSchema",
    "id" : "32",
    "label" : {
      "IRI-based" : "string"
    }
  }, {
    "iri" : "http://www.w3.org/2001/XMLSchema#string",
    "baseIri" : "http://www.w3.org/2001/XMLSchema",
    "id" : "9",
    "label" : {
      "IRI-based" : "string"
    }
  }, {
    "iri" : "http://www.w3.org/2001/XMLSchema#dateTime",
    "baseIri" : "http://www.w3.org/2001/XMLSchema",
    "id" : "31",
    "label" : {
      "IRI-based" : "dateTime"
    }
  }, {
    "iri" : "http://www.w3.org/2001/XMLSchema#double",
    "baseIri" : "http://www.w3.org/2001/XMLSchema",
    "id" : "33",
    "label" : {
      "IRI-based" : "double"
    }
  }, {
    "iri" : "http://www.w3.org/2001/XMLSchema#string",
    "baseIri" : "http://www.w3.org/2001/XMLSchema",
    "id" : "25",
    "label" : {
      "IRI-based" : "string"
    }
  }, {
    "iri" : "http://www.w3.org/2001/XMLSchema#string",
    "baseIri" : "http://www.w3.org/2001/XMLSchema",
    "id" : "35",
    "label" : {
      "IRI-based" : "string"
    }
  }, {
    "iri" : "https://w3id.org/mdo/provenance/ReferenceAgent",
    "baseIri" : "https://w3id.org/mdo/provenance",
    "instances" : 0,
    "label" : {
      "IRI-based" : "ReferenceAgent"
    },
    "comment" : {
      "en" : "A reference agent is the representation of the reference that the material data refers to."
    },
    "id" : "1",
    "superClasses" : [ "18" ]
  }, {
    "iri" : "https://w3id.org/mdo/core/PhysicalProperty",
    "baseIri" : "https://w3id.org/mdo/core",
    "instances" : 0,
    "label" : {
      "IRI-based" : "PhysicalProperty"
    },
    "comment" : {
      "en" : "Properties of structures or materials that are not influenced by calculations."
    },
    "attributes" : [ "external" ],
    "id" : "12",
    "superClasses" : [ "4" ]
  } ],
  "property" : [ {
    "id" : "0",
    "type" : "owl:datatypeProperty"
  }, {
    "id" : "3",
    "type" : "owl:objectProperty"
  }, {
    "id" : "6",
    "type" : "owl:objectProperty"
  }, {
    "id" : "8",
    "type" : "owl:datatypeProperty"
  }, {
    "id" : "11",
    "type" : "rdfs:SubClassOf"
  }, {
    "id" : "13",
    "type" : "rdfs:SubClassOf"
  }, {
    "id" : "16",
    "type" : "rdfs:SubClassOf"
  }, {
    "id" : "19",
    "type" : "rdfs:SubClassOf"
  }, {
    "id" : "23",
    "type" : "owl:objectProperty"
  }, {
    "id" : "24",
    "type" : "owl:datatypeProperty"
  }, {
    "id" : "26",
    "type" : "owl:objectProperty"
  }, {
    "id" : "28",
    "type" : "owl:datatypeProperty"
  }, {
    "id" : "30",
    "type" : "owl:datatypeProperty"
  }, {
    "id" : "34",
    "type" : "owl:datatypeProperty"
  }, {
    "id" : "36",
    "type" : "owl:datatypeProperty"
  }, {
    "id" : "37",
    "type" : "owl:datatypeProperty"
  }, {
    "id" : "38",
    "type" : "owl:disjointWith"
  }, {
    "id" : "39",
    "type" : "owl:someValuesFrom"
  }, {
    "id" : "40",
    "type" : "owl:objectProperty"
  }, {
    "id" : "41",
    "type" : "owl:objectProperty"
  }, {
    "id" : "42",
    "type" : "owl:datatypeProperty"
  }, {
    "id" : "43",
    "type" : "owl:datatypeProperty"
  }, {
    "id" : "44",
    "type" : "owl:objectProperty"
  }, {
    "id" : "45",
    "type" : "owl:datatypeProperty"
  } ],
  "propertyAttribute" : [ {
    "iri" : "https://w3id.org/mdo/provenance/hasPublicationTitle",
    "baseIri" : "https://w3id.org/mdo/provenance",
    "range" : "2",
    "label" : {
      "IRI-based" : "hasPublicationTitle"
    },
    "domain" : "1",
    "comment" : {
      "en" : "To represent the title of the reference."
    },
    "attributes" : [ "datatype" ],
    "id" : "0"
  }, {
    "iri" : "https://w3id.org/mdo/core/relatesToStructure",
    "baseIri" : "https://w3id.org/mdo/core",
    "range" : "5",
    "label" : {
      "IRI-based" : "relatesToStructure"
    },
    "domain" : "4",
    "comment" : {
      "en" : "To represent a property relates to a structure."
    },
    "attributes" : [ "object", "external" ],
    "id" : "3"
  }, {
    "iri" : "https://w3id.org/mdo/core/hasInputStructure",
    "baseIri" : "https://w3id.org/mdo/core",
    "range" : "5",
    "label" : {
      "IRI-based" : "hasInputStructure"
    },
    "domain" : "7",
    "comment" : {
      "en" : "To represent a calculation takes a structure as the input."
    },
    "attributes" : [ "object", "external" ],
    "id" : "6"
  }, {
    "iri" : "https://w3id.org/mdo/core/hasPropertyName",
    "baseIri" : "https://w3id.org/mdo/core",
    "range" : "9",
    "label" : {
      "IRI-based" : "hasPropertyName"
    },
    "domain" : "4",
    "comment" : {
      "en" : "To represent the name of the property."
    },
    "attributes" : [ "external", "datatype" ],
    "id" : "8"
  }, {
    "range" : "4",
    "domain" : "12",
    "attributes" : [ "anonymous", "object" ],
    "id" : "11"
  }, {
    "range" : "4",
    "domain" : "10",
    "attributes" : [ "anonymous", "object" ],
    "id" : "13"
  }, {
    "range" : "18",
    "domain" : "17",
    "attributes" : [ "anonymous", "object" ],
    "id" : "16"
  }, {
    "range" : "18",
    "domain" : "1",
    "attributes" : [ "anonymous", "object" ],
    "id" : "19"
  }, {
    "iri" : "https://w3id.org/mdo/core/hasInputProperty",
    "baseIri" : "https://w3id.org/mdo/core",
    "range" : "4",
    "label" : {
      "IRI-based" : "hasInputProperty"
    },
    "domain" : "7",
    "comment" : {
      "en" : "To represent a calculation takes a property as the input."
    },
    "attributes" : [ "object", "external" ],
    "id" : "23"
  }, {
    "iri" : "https://w3id.org/mdo/provenance/hasAuthorName",
    "baseIri" : "https://w3id.org/mdo/provenance",
    "range" : "25",
    "label" : {
      "IRI-based" : "hasAuthorName"
    },
    "domain" : "1",
    "comment" : {
      "en" : "To represent the author's name of the reference."
    },
    "attributes" : [ "datatype" ],
    "id" : "24"
  }, {
    "iri" : "https://w3id.org/mdo/core/hasOutputStructure",
    "baseIri" : "https://w3id.org/mdo/core",
    "range" : "5",
    "label" : {
      "IRI-based" : "hasOutputStructure"
    },
    "domain" : "7",
    "comment" : {
      "en" : "To represent a calculation outputs a structure after computing."
    },
    "attributes" : [ "object", "external" ],
    "id" : "26"
  }, {
    "iri" : "https://w3id.org/mdo/core/hasID",
    "baseIri" : "https://w3id.org/mdo/core",
    "range" : "29",
    "label" : {
      "IRI-based" : "hasID"
    },
    "domain" : "7",
    "comment" : {
      "en" : "To represent the unique ID of a calculation from a database."
    },
    "attributes" : [ "external", "datatype" ],
    "id" : "28"
  }, {
    "iri" : "https://w3id.org/mdo/provenance/hasPublicationDateTime",
    "baseIri" : "https://w3id.org/mdo/provenance",
    "range" : "31",
    "label" : {
      "IRI-based" : "hasPublicationDateTime"
    },
    "domain" : "1",
    "comment" : {
      "en" : "To represent the publication datetime of the reference."
    },
    "attributes" : [ "datatype" ],
    "id" : "30"
  }, {
    "iri" : "https://w3id.org/mdo/core/hasPropertyValue",
    "baseIri" : "https://w3id.org/mdo/core",
    "range" : "33",
    "label" : {
      "IRI-based" : "hasPropertyValue"
    },
    "domain" : "4",
    "comment" : {
      "en" : "To represent the numerical value of the property."
    },
    "attributes" : [ "external", "datatype" ],
    "id" : "34"
  }, {
    "iri" : "https://w3id.org/mdo/core/hasUnit",
    "baseIri" : "https://w3id.org/mdo/core",
    "range" : "20",
    "label" : {
      "IRI-based" : "hasUnit"
    },
    "domain" : "4",
    "comment" : {
      "en" : "To represent the name of the unit."
    },
    "attributes" : [ "external", "datatype" ],
    "id" : "36"
  }, {
    "iri" : "https://w3id.org/mdo/provenance/hasDOI",
    "baseIri" : "https://w3id.org/mdo/provenance",
    "range" : "32",
    "label" : {
      "IRI-based" : "hasDOI"
    },
    "domain" : "1",
    "comment" : {
      "en" : "To represent the DOI number of the reference."
    },
    "attributes" : [ "datatype" ],
    "id" : "37"
  }, {
    "range" : "12",
    "domain" : "10",
    "attributes" : [ "anonymous", "object" ],
    "id" : "38"
  }, {
    "iri" : "http://www.w3.org/ns/prov#wasAssociatedWith",
    "baseIri" : "http://www.w3.org/ns/prov",
    "range" : "17",
    "label" : {
      "IRI-based" : "wasAssociatedWith"
    },
    "domain" : "7",
    "attributes" : [ "someValues", "object", "external" ],
    "id" : "39"
  }, {
    "iri" : "http://www.w3.org/ns/prov#wasAttributedTo",
    "baseIri" : "http://www.w3.org/ns/prov",
    "range" : "14",
    "label" : {
      "IRI-based" : "wasAttributedTo"
    },
    "domain" : "14",
    "attributes" : [ "object", "external" ],
    "id" : "40"
  }, {
    "iri" : "https://w3id.org/mdo/core/relatesToMaterial",
    "baseIri" : "https://w3id.org/mdo/core",
    "range" : "22",
    "label" : {
      "IRI-based" : "relatesToMaterial"
    },
    "domain" : "5",
    "comment" : {
      "en" : "To represent a structure relates to a material."
    },
    "attributes" : [ "object", "external" ],
    "id" : "41"
  }, {
    "iri" : "https://w3id.org/mdo/provenance/hasSoftwareName",
    "baseIri" : "https://w3id.org/mdo/provenance",
    "range" : "35",
    "label" : {
      "IRI-based" : "hasSoftwareName"
    },
    "cardinality" : "1",
    "domain" : "17",
    "comment" : {
      "en" : "To respresent the software's name."
    },
    "attributes" : [ "datatype" ],
    "id" : "42"
  }, {
    "iri" : "https://w3id.org/mdo/provenance/hasURL",
    "baseIri" : "https://w3id.org/mdo/provenance",
    "range" : "15",
    "label" : {
      "IRI-based" : "hasURL"
    },
    "domain" : "1",
    "comment" : {
      "en" : "To represent the URL of a reference."
    },
    "attributes" : [ "datatype" ],
    "id" : "43"
  }, {
    "iri" : "https://w3id.org/mdo/core/hasOutputCalculatedProperty",
    "baseIri" : "https://w3id.org/mdo/core",
    "range" : "10",
    "label" : {
      "IRI-based" : "hasOutputCalculatedProperty"
    },
    "domain" : "27",
    "comment" : {
      "en" : "To represent a calculation outputs a calculated property after computing."
    },
    "attributes" : [ "object", "external" ],
    "id" : "44"
  }, {
    "iri" : "https://w3id.org/mdo/provenance/hasDatabaseName",
    "baseIri" : "https://w3id.org/mdo/provenance",
    "range" : "21",
    "label" : {
      "IRI-based" : "hasDatabaseName"
    },
    "domain" : "1",
    "comment" : {
      "en" : "To represent the database's name."
    },
    "attributes" : [ "datatype" ],
    "id" : "45"
  } ]
}