[ {
  "@id" : "http://purl.org/dc/terms/contributor",
  "@type" : [ "http://www.w3.org/2002/07/owl#AnnotationProperty" ]
}, {
  "@id" : "http://purl.org/dc/terms/created",
  "@type" : [ "http://www.w3.org/2002/07/owl#AnnotationProperty" ]
}, {
  "@id" : "http://purl.org/dc/terms/creator",
  "@type" : [ "http://www.w3.org/2002/07/owl#AnnotationProperty" ]
}, {
  "@id" : "http://purl.org/dc/terms/license",
  "@type" : [ "http://www.w3.org/2002/07/owl#AnnotationProperty" ]
}, {
  "@id" : "http://purl.org/vocab/vann/preferredNamespacePrefix",
  "@type" : [ "http://www.w3.org/2002/07/owl#AnnotationProperty" ]
}, {
  "@id" : "http://purl.org/vocab/vann/preferredNamespaceUri",
  "@type" : [ "http://www.w3.org/2002/07/owl#AnnotationProperty" ]
}, {
  "@id" : "https://w3id.org/mdo/full/",
  "@type" : [ "http://www.w3.org/2002/07/owl#Ontology" ],
  "http://purl.org/dc/terms/contributor" : [ {
    "@value" : "Patrick Lambrix"
  }, {
    "@value" : "Rickard Armiento"
  } ],
  "http://purl.org/dc/terms/created" : [ {
    "@value" : "2019-11-07"
  } ],
  "http://purl.org/dc/terms/creator" : [ {
    "@value" : "Huanyu Li"
  } ],
  "http://purl.org/dc/terms/license" : [ {
    "@value" : "https://github.com/huanyu-li/Materials-Design-Ontology/blob/master/LICENSE"
  } ],
  "http://purl.org/vocab/vann/preferredNamespacePrefix" : [ {
    "@value" : "mdo"
  } ],
  "http://purl.org/vocab/vann/preferredNamespaceUri" : [ {
    "@value" : "https://w3id.org/mdo/full/1.0"
  } ],
  "http://www.w3.org/2000/01/rdf-schema#comment" : [ {
    "@language" : "en",
    "@value" : "This is the Materials Design Ontology."
  } ],
  "http://www.w3.org/2000/01/rdf-schema#label" : [ {
    "@value" : "Materials Design Ontology"
  } ],
  "http://www.w3.org/2000/01/rdf-schema#seeAlso" : [ {
    "@value" : "https://github.com/huanyu-li/Materials-Design-Ontology"
  } ],
  "http://www.w3.org/2002/07/owl#imports" : [ {
    "@id" : "https://w3id.org/mdo/calculation/1.0"
  }, {
    "@id" : "https://w3id.org/mdo/core/1.0"
  }, {
    "@id" : "https://w3id.org/mdo/provenance/1.0"
  }, {
    "@id" : "https://w3id.org/mdo/structure/1.0"
  } ],
  "http://www.w3.org/2002/07/owl#versionIRI" : [ {
    "@id" : "https://w3id.org/mdo/full/1.0"
  } ],
  "http://www.w3.org/2002/07/owl#versionInfo" : [ {
    "@value" : "1.0"
  } ]
} ]